etech_reading/__init__.py
etech_reading/analyzer.py
etech_reading/reader.py
etech_reading-1.0.2.dist-info/licenses/LICENSE
etech_reading-1.0.2.dist-info/METADATA
etech_reading-1.0.2.dist-info/WHEEL
etech_reading-1.0.2.dist-info/entry_points.txt
etech_reading-1.0.2.dist-info/top_level.txt
etech_reading-1.0.2.dist-info/RECORD
