Metadata-Version: 2.4
Name: etech-reading
Version: 1.0.2
Summary: Fast Reading System using RSVP Technology
Home-page: https://github.com/eOS/etech-reading
Author: eOS
Author-email: eOS <eymenomersenyigit@gmail.com>
License: MIT
Project-URL: Homepage, https://github.com/eOS/etech-reading
Project-URL: Bug Tracker, https://github.com/eOS/etech-reading/issues
Project-URL: Documentation, https://github.com/eOS/etech-reading#readme
Project-URL: Source Code, https://github.com/eOS/etech-reading
Keywords: reading,speed,rsvp,rapid-serial-visual-presentation,text-analysis
Classifier: Development Status :: 4 - Beta
Classifier: Environment :: X11 Applications :: Qt
Classifier: Intended Audience :: End Users/Desktop
Classifier: Intended Audience :: Education
Classifier: License :: OSI Approved :: MIT License
Classifier: Operating System :: OS Independent
Classifier: Programming Language :: Python :: 3
Classifier: Programming Language :: Python :: 3.7
Classifier: Programming Language :: Python :: 3.8
Classifier: Programming Language :: Python :: 3.9
Classifier: Programming Language :: Python :: 3.10
Classifier: Programming Language :: Python :: 3.11
Classifier: Programming Language :: Python :: 3.12
Classifier: Topic :: Education
Classifier: Topic :: Text Processing
Requires-Python: >=3.7
License-File: LICENSE
Requires-Dist: PyQt5>=5.15.0
Requires-Dist: PyQtWebEngine>=5.15.0
Provides-Extra: dev
Requires-Dist: pytest>=6.0; extra == "dev"
Requires-Dist: pytest-cov>=2.10; extra == "dev"
Requires-Dist: black>=21.0; extra == "dev"
Requires-Dist: flake8>=3.9; extra == "dev"
Requires-Dist: mypy>=0.910; extra == "dev"
Dynamic: author
Dynamic: home-page
Dynamic: license-file
Dynamic: requires-python
